drawyolo/__init__.py
drawyolo/draw.py
drawyolo/main.py
drawyolo-0.1.3.dist-info/LICENSE
drawyolo-0.1.3.dist-info/METADATA
drawyolo-0.1.3.dist-info/WHEEL
drawyolo-0.1.3.dist-info/entry_points.txt
drawyolo-0.1.3.dist-info/RECORD
