Metadata-Version: 2.3
Name: drawyolo
Version: 0.1.3
Summary: Draws boxes on images from annotations in YOLO format
License: Apache-2.0
Keywords: yolo,command-line interface
Author: Robert Turnbull
Author-email: robert.turnbull@unimelb.edu.au
Requires-Python: >=3.10,<4
Classifier: Intended Audience :: Science/Research
Classifier: License :: OSI Approved :: Apache Software License
Classifier: Programming Language :: Python :: 3
Classifier: Programming Language :: Python :: 3.10
Classifier: Programming Language :: Python :: 3.11
Classifier: Programming Language :: Python :: 3.12
Classifier: Programming Language :: Python :: 3.13
Classifier: Topic :: Software Development :: Libraries :: Python Modules
Requires-Dist: opencv-python (>=4.9.0.80)
Requires-Dist: rich (>=13.7.0)
Requires-Dist: typer (>=0.9.0)
Requires-Dist: ultralytics (>=8.1.0)
Project-URL: Documentation, https://rbturnbull.github.io/drawyolo
Project-URL: Homepage, https://github.com/rbturnbull/drawyolo/
Project-URL: Repository, https://github.com/rbturnbull/drawyolo/
